fastrometry/__init__.py
fastrometry/catalogue.py
fastrometry/fastrometry.py
fastrometry/cython_code/PSE.cp310-win_amd64.pyd
fastrometry/cython_code/WCS.cp310-win_amd64.pyd
fastrometry/cython_code/__init__.py
fastrometry-1.0.10.dist-info/LICENSE
fastrometry-1.0.10.dist-info/METADATA
fastrometry-1.0.10.dist-info/WHEEL
fastrometry-1.0.10.dist-info/entry_points.txt
fastrometry-1.0.10.dist-info/top_level.txt
fastrometry-1.0.10.dist-info/RECORD
