Metadata-Version: 2.1
Name: fastrometry
Version: 1.0.10
Summary: Astrometry package written in Python
Author: Cameron Leahy, Joseph Postma
Author-email: cameron.leahy@ucalgary.ca, joepostma@live.ca
Project-URL: Homepage, https://github.com/user29A/fastrometry/wiki
Project-URL: Download, https://pypi.org/project/fastrometry/#files
Project-URL: Source code, https://github.com/user29A/fastrometry
Project-URL: Bug tracker, https://github.com/user29A/fastrometry/issues
Project-URL: Documentation, https://github.com/user29A/fastrometry/wiki
Classifier: Programming Language :: Python
Classifier: Programming Language :: Python :: 3
Classifier: Programming Language :: Python :: 3.10
Classifier: Programming Language :: Python :: Implementation :: CPython
Classifier: License :: OSI Approved :: GNU General Public License (GPL)
Classifier: Development Status :: 5 - Production/Stable
Classifier: Intended Audience :: Science/Research
Classifier: Topic :: Scientific/Engineering :: Astronomy
Requires-Python: >=3.10
License-File: LICENSE
Requires-Dist: astropy (>=5.1)
Requires-Dist: numpy (>=1.22.4)
Requires-Dist: scipy (>=1.8.1)
Requires-Dist: AstraCarta (>=1.0.33)
Requires-Dist: matplotlib (>=3.5.0)
